request_filter_groups/__init__.py
request_filter_groups/filter_groups.py
request_filter_groups-0.0.4.dist-info/METADATA
request_filter_groups-0.0.4.dist-info/WHEEL
request_filter_groups-0.0.4.dist-info/top_level.txt
request_filter_groups-0.0.4.dist-info/RECORD
