Metadata-Version: 2.1
Name: request-filter-groups
Version: 0.0.4
Summary: Uses filter groups to validate requests
Home-page: https://github.com/marshall7m/request-filter-groups
Author: Marshall Mamiya
License: Apache 2.0
Classifier: Framework :: Flask
Classifier: Intended Audience :: Developers
Classifier: License :: OSI Approved :: Apache Software License
Classifier: Operating System :: OS Independent
Classifier: Programming Language :: Python :: 3
Requires-Dist: flask
Requires-Dist: validator (==0.7.1)
Requires-Dist: jsonpath-ng (==1.5.3)
Provides-Extra: tests
Requires-Dist: pytest ; extra == 'tests'
